grovers_visualizer/__init__.py
grovers_visualizer/__main__.py
grovers_visualizer/args.py
grovers_visualizer/circuit.py
grovers_visualizer/cli.py
grovers_visualizer/main.py
grovers_visualizer/simulation.py
grovers_visualizer/state.py
grovers_visualizer/utils.py
grovers_visualizer/visualization.py
grovers_visualizer/plot/__init__.py
grovers_visualizer/plot/amplitudes.py
grovers_visualizer/plot/circle.py
grovers_visualizer/plot/sine.py
grovers_visualizer/ui/__init__.py
grovers_visualizer/ui/dpg.py
grovers_visualizer-0.5.0.dist-info/METADATA
grovers_visualizer-0.5.0.dist-info/WHEEL
grovers_visualizer-0.5.0.dist-info/entry_points.txt
grovers_visualizer-0.5.0.dist-info/licenses/LICENSE
grovers_visualizer-0.5.0.dist-info/RECORD
