Metadata-Version: 2.4
Name: grovers-visualizer
Version: 0.5.0
Summary: A tiny Python package that steps through Grover’s Search algorithm.
Project-URL: Source, https://github.com/kristoferssolo/grovers-visualizer
Project-URL: Tracker, https://github.com/kristoferssolo/grovers-visualizer/issues
Author-email: Kristofers Solo <dev@kristofers.xyz>
License: MIT License
License-File: LICENSE
Requires-Python: >=3.10
Requires-Dist: numpy==2.2.4
Requires-Dist: pyqt6==6.9.0
Requires-Dist: qiskit-aer==0.17.0
Requires-Dist: qiskit[visualization]==2.0.0
Provides-Extra: ui
Requires-Dist: dearpygui==2.0.0; extra == 'ui'
